hashed/__init__.py
hashed/buffer_reader.py
hashed/cli.py
hashed/common.py
hashed/hash.py
hashed/hash_lib.py
hashed/sha256.py
hashed/sha512.py
test/__init__.py
test/test_sha256.py
test/test_sha512.py
hashed-2.2.0.dist-info/LICENSE
hashed-2.2.0.dist-info/METADATA
hashed-2.2.0.dist-info/WHEEL
hashed-2.2.0.dist-info/top_level.txt
hashed-2.2.0.dist-info/RECORD
