Metadata-Version: 2.1
Name: hashed
Version: 2.2.0
Summary: Provides secured hashes for given data
Home-page: https://github.com/mukund26/hashed
Author: Mukund Agarwal
Author-email: m.agarwalhp@gmail.com
License: MIT
Keywords: python,hashing,sha256,sha512
Classifier: Development Status :: 3 - Alpha
Classifier: Intended Audience :: Developers
Classifier: Programming Language :: Python :: 3
Classifier: Operating System :: MacOS :: MacOS X
Classifier: Operating System :: Microsoft :: Windows
Requires-Python: >=3.6
License-File: LICENSE
